getmyip/__init__.py
getmyip/getmyip.py
getmyip/getmyipmain.py
getmyip46-24.12.28.data/scripts/getmyip
getmyip46-24.12.28.dist-info/LICENSE.txt
getmyip46-24.12.28.dist-info/METADATA
getmyip46-24.12.28.dist-info/WHEEL
getmyip46-24.12.28.dist-info/top_level.txt
getmyip46-24.12.28.dist-info/RECORD
