Metadata-Version: 2.1
Name: getmyip46
Version: 24.12.28
Summary: print the external ip address (v4 or v6)
Home-page: https://github.com/Glocktober/getmyip
Author: gunville
Author-email: rk13088@yahoo.com
Project-URL: repo, https://github.com/Glocktober/getmyip.git
Project-URL: overview, https://github.com/Glocktober/getmyip/blob/master/README.md
Keywords: 'ip network'
Classifier: Programming Language :: Python :: 3
Classifier: License :: OSI Approved :: MIT License
Classifier: Operating System :: OS Independent
Requires-Python: >=3.6
License-File: LICENSE.txt
Requires-Dist: Requests>=2.32.0
